setup.py
src/ua2/__init__.py
src/ua2.celery.egg-info/PKG-INFO
src/ua2.celery.egg-info/SOURCES.txt
src/ua2.celery.egg-info/dependency_links.txt
src/ua2.celery.egg-info/eager_resources.txt
src/ua2.celery.egg-info/namespace_packages.txt
src/ua2.celery.egg-info/not-zip-safe
src/ua2.celery.egg-info/top_level.txt
src/ua2/celery/__init__.py
src/ua2/celery/auth.py
src/ua2/celery/urls.py
src/ua2/celery/views.py