Metadata-Version: 1.0
Name: ua2.celery
Version: 0.0.1
Summary: Extended handlers and helpers worh with celery
Home-page: https://bitbucket.org/ua2web/ua2.celery
Author: Vic
Author-email: vic@ua2web.com
License: BSD License
Platform: UNKNOWN
